{
  "updated_at": "2026-03-17T07:36:22.362486",
  "prices": {
    "428560": 16200.0,
    "005380": 522000.0,
    "005930": 193900.0,
    "000660": 970000.0,
    "030200": 60000.0,
    "055550": 91200.0,
    "316140": 32600.0,
    "360750": 24715.0,
    "133690": 162355.0,
    "379810": 24325.0,
    "041510": 99500.0,
    "102110": 84610.0,
    "091160": 99470.0,
    "010120": 762000.0,
    "005290": 49250.0,
    "357780": 422000.0,
    "489790": 76900.0,
    "102120": 11760.0,
    "196170": 354500.0,
    "017960": 48650.0,
    "064350": 192900.0,
    "103590": 78200.0,
    "483340": 17430.0,
    "396500": 33100.0,
    "244580": 13220.0,
    "139230": 16015.0,
    "377300": 60100.0,
    "364970": 8275.0,
    "015760": 48200.0,
    "229200": 19650.0,
    "URNM": 64.18,
    "URA": 49.95,
    "AAAU": 49.44,
    "SLVR": 62.8,
    "042700": 301000.0,
    "079550": 705000.0,
    "440110": 62700.0,
    "329180": 587000.0,
    "006800": 69100.0,
    "034020": 104400.0,
    "ORCL": 155.97
  },
  "price_details": {
    "041510": {
      "price": 99500.0,
      "source": "naver",
      "timestamp": "2026-03-17T07:36:18.626731"
    },
    "064350": {
      "price": 192900.0,
      "source": "naver",
      "timestamp": "2026-03-17T07:36:15.664235"
    },
    "091160": {
      "price": 99470.0,
      "source": "naver",
      "timestamp": "2026-03-17T07:35:28.644878"
    },
    "360750": {
      "price": 24715.0,
      "source": "naver",
      "timestamp": "2026-03-17T07:36:03.015369"
    },
    "379810": {
      "price": 24325.0,
      "source": "naver",
      "timestamp": "2026-03-17T07:35:42.510073"
    },
    "377300": {
      "price": 60100.0,
      "source": "naver",
      "timestamp": "2026-03-17T07:35:58.815157"
    },
    "139230": {
      "price": 16015.0,
      "source": "naver",
      "timestamp": "2026-03-17T07:35:34.805187"
    },
    "364970": {
      "price": 8275.0,
      "source": "naver",
      "timestamp": "2026-03-17T07:35:37.858178"
    },
    "102120": {
      "price": 11760.0,
      "source": "naver",
      "timestamp": "2026-03-17T07:35:57.439257"
    },
    "102110": {
      "price": 84610.0,
      "source": "naver",
      "timestamp": "2026-03-17T07:36:00.155154"
    },
    "357780": {
      "price": 422000.0,
      "source": "naver",
      "timestamp": "2026-03-17T07:35:49.796386"
    },
    "316140": {
      "price": 32600.0,
      "source": "naver",
      "timestamp": "2026-03-17T07:35:55.871782"
    },
    "196170": {
      "price": 354500.0,
      "source": "naver",
      "timestamp": "2026-03-17T07:35:41.017841"
    },
    "133690": {
      "price": 162355.0,
      "source": "naver",
      "timestamp": "2026-03-17T07:35:46.737977"
    },
    "010120": {
      "price": 762000.0,
      "source": "naver",
      "timestamp": "2026-03-17T07:35:51.371460"
    },
    "005290": {
      "price": 49250.0,
      "source": "naver",
      "timestamp": "2026-03-17T07:36:19.991571"
    },
    "244580": {
      "price": 13220.0,
      "source": "naver",
      "timestamp": "2026-03-17T07:35:36.314305"
    },
    "055550": {
      "price": 91200.0,
      "source": "naver",
      "timestamp": "2026-03-17T07:35:39.390719"
    },
    "015760": {
      "price": 48200.0,
      "source": "naver",
      "timestamp": "2026-03-17T07:36:04.532267"
    },
    "483340": {
      "price": 17430.0,
      "source": "naver",
      "timestamp": "2026-03-17T07:35:45.405472"
    },
    "017960": {
      "price": 48650.0,
      "source": "naver",
      "timestamp": "2026-03-17T07:35:31.650350"
    },
    "428560": {
      "price": 16200.0,
      "source": "naver",
      "timestamp": "2026-03-17T07:36:01.685224"
    },
    "000660": {
      "price": 970000.0,
      "source": "naver",
      "timestamp": "2026-03-17T07:36:12.858528"
    },
    "005930": {
      "price": 193900.0,
      "source": "naver",
      "timestamp": "2026-03-17T07:36:11.518481"
    },
    "103590": {
      "price": 78200.0,
      "source": "naver",
      "timestamp": "2026-03-17T07:35:43.880219"
    },
    "030200": {
      "price": 60000.0,
      "source": "naver",
      "timestamp": "2026-03-17T07:36:10.014319"
    },
    "489790": {
      "price": 76900.0,
      "source": "naver",
      "timestamp": "2026-03-17T07:36:14.281161"
    },
    "229200": {
      "price": 19650.0,
      "source": "naver",
      "timestamp": "2026-03-17T07:35:52.699362"
    },
    "005380": {
      "price": 522000.0,
      "source": "naver",
      "timestamp": "2026-03-17T07:35:30.142467"
    },
    "396500": {
      "price": 33100.0,
      "source": "naver",
      "timestamp": "2026-03-17T07:36:17.072409"
    },
    "URNM": {
      "price": 64.18,
      "source": "yahoo",
      "timestamp": "2026-03-16T16:00:00"
    },
    "URA": {
      "price": 49.95,
      "source": "yahoo",
      "timestamp": "2026-03-16T16:00:00"
    },
    "AAAU": {
      "price": 49.44,
      "source": "yahoo",
      "timestamp": "2026-03-16T16:00:00"
    },
    "SLVR": {
      "price": 62.8,
      "source": "yahoo",
      "timestamp": "2026-03-16T16:00:00"
    },
    "042700": {
      "price": 301000.0,
      "source": "naver",
      "timestamp": "2026-03-17T07:36:08.623602"
    },
    "079550": {
      "price": 705000.0,
      "source": "naver",
      "timestamp": "2026-03-17T07:36:05.899176"
    },
    "440110": {
      "price": 62700.0,
      "source": "naver",
      "timestamp": "2026-03-17T07:35:48.506557"
    },
    "329180": {
      "price": 587000.0,
      "source": "naver",
      "timestamp": "2026-03-17T07:36:07.270084"
    },
    "006800": {
      "price": 69100.0,
      "source": "naver",
      "timestamp": "2026-03-17T07:35:54.313291"
    },
    "034020": {
      "price": 104400.0,
      "source": "naver",
      "timestamp": "2026-03-17T07:35:33.273029"
    },
    "ORCL": {
      "price": 155.97,
      "source": "yahoo",
      "timestamp": "2026-03-16T16:00:00"
    }
  }
}