{
  "updated_at": "2026-05-06T08:44:13.753772",
  "prices": {
    "428560": 16045.0,
    "005380": 550000.0,
    "005930": 266000.0,
    "000660": 1601000.0,
    "030200": 58500.0,
    "055550": 97300.0,
    "316140": 32600.0,
    "360750": 26285.0,
    "133690": 181835.0,
    "0117V0": 23920.0,
    "379810": 27210.0,
    "041510": 92200.0,
    "102110": 113170.0,
    "091160": 140020.0,
    "010120": 315500.0,
    "005290": 59100.0,
    "357780": 466000.0,
    "489790": 89700.0,
    "102120": 15250.0,
    "196170": 363500.0,
    "017960": 47750.0,
    "064350": 262000.0,
    "103590": 142200.0,
    "483340": 23745.0,
    "396500": 45470.0,
    "244580": 11925.0,
    "139230": 20475.0,
    "377300": 63300.0,
    "364970": 7880.0,
    "015760": 45050.0,
    "229200": 20235.0,
    "URNM": 64.82,
    "URA": 54.2,
    "AAAU": 44.91,
    "SLVR": 57.51,
    "042700": 394500.0,
    "079550": 979000.0,
    "440110": 78800.0,
    "329180": 648000.0,
    "006800": 83800.0,
    "034020": 127000.0,
    "ORCL": 185.35,
    "161890": 86900.0,
    "VRT": 341.02,
    "ALM": 20.03,
    "010130": 1747000.0,
    "ETN": 410.86,
    "TSM": 394.41,
    "DLR": 196.69,
    "ROK": 435.93
  },
  "price_details": {
    "041510": {
      "price": 92200.0,
      "source": "naver",
      "timestamp": "2026-05-06T08:43:34.270023"
    },
    "064350": {
      "price": 262000.0,
      "source": "naver",
      "timestamp": "2026-05-06T08:43:16.953443"
    },
    "091160": {
      "price": 140020.0,
      "source": "naver",
      "timestamp": "2026-05-06T08:43:12.278068"
    },
    "360750": {
      "price": 26285.0,
      "source": "naver",
      "timestamp": "2026-05-06T08:43:39.062983"
    },
    "379810": {
      "price": 27210.0,
      "source": "naver",
      "timestamp": "2026-05-06T08:43:41.928479"
    },
    "377300": {
      "price": 63300.0,
      "source": "naver",
      "timestamp": "2026-05-06T08:43:31.125635"
    },
    "139230": {
      "price": 20475.0,
      "source": "naver",
      "timestamp": "2026-05-06T08:44:04.323897"
    },
    "364970": {
      "price": 7880.0,
      "source": "naver",
      "timestamp": "2026-05-06T08:43:23.313146"
    },
    "102120": {
      "price": 15250.0,
      "source": "naver",
      "timestamp": "2026-05-06T08:43:56.840119"
    },
    "102110": {
      "price": 113170.0,
      "source": "naver",
      "timestamp": "2026-05-06T08:43:37.545502"
    },
    "357780": {
      "price": 466000.0,
      "source": "naver",
      "timestamp": "2026-05-06T08:43:54.030769"
    },
    "316140": {
      "price": 32600.0,
      "source": "naver",
      "timestamp": "2026-05-06T08:44:02.976949"
    },
    "196170": {
      "price": 363500.0,
      "source": "naver",
      "timestamp": "2026-05-06T08:43:21.803437"
    },
    "133690": {
      "price": 181835.0,
      "source": "naver",
      "timestamp": "2026-05-06T08:43:52.265265"
    },
    "010120": {
      "price": 315500.0,
      "source": "naver",
      "timestamp": "2026-05-06T08:44:07.143264"
    },
    "005290": {
      "price": 59100.0,
      "source": "naver",
      "timestamp": "2026-05-06T08:43:45.086689"
    },
    "244580": {
      "price": 11925.0,
      "source": "naver",
      "timestamp": "2026-05-06T08:43:40.573031"
    },
    "055550": {
      "price": 97300.0,
      "source": "naver",
      "timestamp": "2026-05-06T08:43:28.020180"
    },
    "015760": {
      "price": 45050.0,
      "source": "naver",
      "timestamp": "2026-05-06T08:43:29.560760"
    },
    "483340": {
      "price": 23745.0,
      "source": "naver",
      "timestamp": "2026-05-06T08:43:59.761590"
    },
    "017960": {
      "price": 47750.0,
      "source": "naver",
      "timestamp": "2026-05-06T08:43:47.943521"
    },
    "428560": {
      "price": 16045.0,
      "source": "naver",
      "timestamp": "2026-05-06T08:43:24.855703"
    },
    "000660": {
      "price": 1601000.0,
      "source": "naver",
      "timestamp": "2026-05-06T08:43:50.749121"
    },
    "005930": {
      "price": 266000.0,
      "source": "naver",
      "timestamp": "2026-05-06T08:43:55.305605"
    },
    "103590": {
      "price": 142200.0,
      "source": "naver",
      "timestamp": "2026-05-06T08:43:18.519061"
    },
    "030200": {
      "price": 58500.0,
      "source": "naver",
      "timestamp": "2026-05-06T08:44:05.815981"
    },
    "489790": {
      "price": 89700.0,
      "source": "naver",
      "timestamp": "2026-05-06T08:43:35.857378"
    },
    "229200": {
      "price": 20235.0,
      "source": "naver",
      "timestamp": "2026-05-06T08:43:15.359752"
    },
    "005380": {
      "price": 550000.0,
      "source": "naver",
      "timestamp": "2026-05-06T08:43:32.661489"
    },
    "396500": {
      "price": 45470.0,
      "source": "naver",
      "timestamp": "2026-05-06T08:43:49.241178"
    },
    "URNM": {
      "price": 64.82,
      "source": "yahoo",
      "timestamp": "2026-05-05T16:00:00"
    },
    "URA": {
      "price": 54.2,
      "source": "yahoo",
      "timestamp": "2026-05-05T16:00:00"
    },
    "AAAU": {
      "price": 44.91,
      "source": "yahoo",
      "timestamp": "2026-05-05T16:00:00"
    },
    "SLVR": {
      "price": 57.51,
      "source": "yahoo",
      "timestamp": "2026-05-05T16:00:00"
    },
    "042700": {
      "price": 394500.0,
      "source": "naver",
      "timestamp": "2026-05-06T08:43:58.448370"
    },
    "079550": {
      "price": 979000.0,
      "source": "naver",
      "timestamp": "2026-05-06T08:43:46.591383"
    },
    "440110": {
      "price": 78800.0,
      "source": "naver",
      "timestamp": "2026-05-06T08:44:01.559665"
    },
    "329180": {
      "price": 648000.0,
      "source": "naver",
      "timestamp": "2026-05-06T08:43:13.845256"
    },
    "006800": {
      "price": 83800.0,
      "source": "naver",
      "timestamp": "2026-05-06T08:44:08.579675"
    },
    "034020": {
      "price": 127000.0,
      "source": "naver",
      "timestamp": "2026-05-06T08:43:43.724372"
    },
    "ORCL": {
      "price": 185.35,
      "source": "yahoo",
      "timestamp": "2026-05-05T16:00:00"
    },
    "161890": {
      "price": 86900.0,
      "source": "naver",
      "timestamp": "2026-05-06T08:43:26.477697"
    },
    "VRT": {
      "price": 341.02,
      "source": "yahoo",
      "timestamp": "2026-05-05T16:00:00"
    },
    "ALM": {
      "price": 20.03,
      "source": "yahoo",
      "timestamp": "2026-05-05T16:00:00"
    },
    "010130": {
      "price": 1747000.0,
      "source": "naver",
      "timestamp": "2026-05-06T08:43:20.256056"
    },
    "ETN": {
      "price": 410.86,
      "source": "yahoo",
      "timestamp": "2026-05-05T16:00:00"
    },
    "TSM": {
      "price": 394.41,
      "source": "yahoo",
      "timestamp": "2026-05-05T16:00:00"
    },
    "DLR": {
      "price": 196.69,
      "source": "yahoo",
      "timestamp": "2026-05-05T16:00:00"
    },
    "ROK": {
      "price": 435.93,
      "source": "yahoo",
      "timestamp": "2026-05-05T16:00:00"
    }
  }
}