{
  "updated_at": "2026-02-11T01:06:14.130794",
  "prices": {
    "428560": 15800.0,
    "005380": 501000.0,
    "005930": 164900.0,
    "000660": 864000.0,
    "030200": 63100.0,
    "055550": 99600.0,
    "316140": 36800.0,
    "360750": 25110.0,
    "133690": 162525.0,
    "379810": 24350.0,
    "041510": 117700.0,
    "102110": 78630.0,
    "091160": 85675.0,
    "010120": 655000.0,
    "005290": 50300.0,
    "357780": 398500.0,
    "489790": 59100.0,
    "102120": 12440.0,
    "196170": 387000.0,
    "017960": 35600.0,
    "064350": 201500.0,
    "103590": 69000.0,
    "483340": 16860.0,
    "396500": 28160.0,
    "244580": 13215.0,
    "139230": 15360.0,
    "377300": 60300.0,
    "364970": 9145.0,
    "015760": 61100.0,
    "229200": 19255.0,
    "URNM": 70.88,
    "URA": 53.5,
    "AAAU": 49.65,
    "SLVR": 69.13,
    "042700": 191200.0,
    "079550": 472000.0,
    "440110": 47950.0
  },
  "price_details": {
    "041510": {
      "price": 117700.0,
      "source": "naver",
      "timestamp": "2026-02-11T01:05:32.123266"
    },
    "064350": {
      "price": 201500.0,
      "source": "naver",
      "timestamp": "2026-02-11T01:06:08.676652"
    },
    "091160": {
      "price": 85675.0,
      "source": "naver",
      "timestamp": "2026-02-11T01:05:40.072724"
    },
    "360750": {
      "price": 25110.0,
      "source": "naver",
      "timestamp": "2026-02-11T01:06:07.461308"
    },
    "379810": {
      "price": 24350.0,
      "source": "naver",
      "timestamp": "2026-02-11T01:05:55.915730"
    },
    "377300": {
      "price": 60300.0,
      "source": "naver",
      "timestamp": "2026-02-11T01:05:34.755207"
    },
    "139230": {
      "price": 15360.0,
      "source": "naver",
      "timestamp": "2026-02-11T01:05:33.352021"
    },
    "364970": {
      "price": 9145.0,
      "source": "naver",
      "timestamp": "2026-02-11T01:05:37.395652"
    },
    "102120": {
      "price": 12440.0,
      "source": "naver",
      "timestamp": "2026-02-11T01:05:36.008365"
    },
    "102110": {
      "price": 78630.0,
      "source": "naver",
      "timestamp": "2026-02-11T01:05:30.720415"
    },
    "357780": {
      "price": 398500.0,
      "source": "naver",
      "timestamp": "2026-02-11T01:05:50.785560"
    },
    "316140": {
      "price": 36800.0,
      "source": "naver",
      "timestamp": "2026-02-11T01:05:44.204602"
    },
    "196170": {
      "price": 387000.0,
      "source": "naver",
      "timestamp": "2026-02-11T01:05:48.312857"
    },
    "133690": {
      "price": 162525.0,
      "source": "naver",
      "timestamp": "2026-02-11T01:05:49.534287"
    },
    "010120": {
      "price": 655000.0,
      "source": "naver",
      "timestamp": "2026-02-11T01:05:46.912569"
    },
    "005290": {
      "price": 50300.0,
      "source": "naver",
      "timestamp": "2026-02-11T01:05:45.636753"
    },
    "244580": {
      "price": 13215.0,
      "source": "naver",
      "timestamp": "2026-02-11T01:06:04.981506"
    },
    "055550": {
      "price": 99600.0,
      "source": "naver",
      "timestamp": "2026-02-11T01:05:41.488923"
    },
    "015760": {
      "price": 61100.0,
      "source": "naver",
      "timestamp": "2026-02-11T01:06:01.110385"
    },
    "483340": {
      "price": 16860.0,
      "source": "naver",
      "timestamp": "2026-02-11T01:06:11.223904"
    },
    "017960": {
      "price": 35600.0,
      "source": "naver",
      "timestamp": "2026-02-11T01:05:53.224729"
    },
    "428560": {
      "price": 15800.0,
      "source": "naver",
      "timestamp": "2026-02-11T01:06:03.747983"
    },
    "000660": {
      "price": 864000.0,
      "source": "naver",
      "timestamp": "2026-02-11T01:05:38.673409"
    },
    "005930": {
      "price": 164900.0,
      "source": "naver",
      "timestamp": "2026-02-11T01:05:59.699900"
    },
    "103590": {
      "price": 69000.0,
      "source": "naver",
      "timestamp": "2026-02-11T01:05:54.704280"
    },
    "030200": {
      "price": 63100.0,
      "source": "naver",
      "timestamp": "2026-02-11T01:05:57.151264"
    },
    "489790": {
      "price": 59100.0,
      "source": "naver",
      "timestamp": "2026-02-11T01:05:58.360735"
    },
    "229200": {
      "price": 19255.0,
      "source": "naver",
      "timestamp": "2026-02-11T01:05:42.784880"
    },
    "005380": {
      "price": 501000.0,
      "source": "naver",
      "timestamp": "2026-02-11T01:05:29.347924"
    },
    "396500": {
      "price": 28160.0,
      "source": "naver",
      "timestamp": "2026-02-11T01:05:51.994544"
    },
    "URNM": {
      "price": 70.88,
      "source": "yahoo",
      "timestamp": "2026-02-10T16:00:00"
    },
    "URA": {
      "price": 53.5,
      "source": "yahoo",
      "timestamp": "2026-02-10T16:00:00"
    },
    "AAAU": {
      "price": 49.65,
      "source": "yahoo",
      "timestamp": "2026-02-10T16:00:00"
    },
    "SLVR": {
      "price": 69.13,
      "source": "yahoo",
      "timestamp": "2026-02-10T16:00:00"
    },
    "042700": {
      "price": 191200.0,
      "source": "naver",
      "timestamp": "2026-02-11T01:06:02.398566"
    },
    "079550": {
      "price": 472000.0,
      "source": "naver",
      "timestamp": "2026-02-11T01:06:06.260563"
    },
    "440110": {
      "price": 47950.0,
      "source": "naver",
      "timestamp": "2026-02-11T01:06:09.956156"
    }
  }
}