{
  "updated_at": "2026-02-13T07:31:47.498461",
  "prices": {
    "428560": 15225.0,
    "005380": 499000.0,
    "005930": 181200.0,
    "000660": 880000.0,
    "030200": 64500.0,
    "055550": 102500.0,
    "316140": 38950.0,
    "360750": 24435.0,
    "133690": 157705.0,
    "379810": 23620.0,
    "041510": 116600.0,
    "102110": 81835.0,
    "091160": 88745.0,
    "010120": 661000.0,
    "005290": 51500.0,
    "357780": 398000.0,
    "489790": 61300.0,
    "102120": 12000.0,
    "196170": 382000.0,
    "017960": 34900.0,
    "064350": 201500.0,
    "103590": 71500.0,
    "483340": 16560.0,
    "396500": 29320.0,
    "244580": 12970.0,
    "139230": 15440.0,
    "377300": 62500.0,
    "364970": 9030.0,
    "015760": 59800.0,
    "229200": 18955.0,
    "URNM": 69.31,
    "URA": 51.75,
    "AAAU": 48.48,
    "SLVR": 62.88,
    "042700": 202500.0,
    "079550": 460000.0,
    "440110": 52200.0
  },
  "price_details": {
    "041510": {
      "price": 116600.0,
      "source": "naver",
      "timestamp": "2026-02-13T07:31:17.902552"
    },
    "064350": {
      "price": 201500.0,
      "source": "naver",
      "timestamp": "2026-02-13T07:31:26.037437"
    },
    "091160": {
      "price": 88745.0,
      "source": "naver",
      "timestamp": "2026-02-13T07:31:31.827666"
    },
    "360750": {
      "price": 24435.0,
      "source": "naver",
      "timestamp": "2026-02-13T07:31:44.139664"
    },
    "379810": {
      "price": 23620.0,
      "source": "naver",
      "timestamp": "2026-02-13T07:31:23.706772"
    },
    "377300": {
      "price": 62500.0,
      "source": "naver",
      "timestamp": "2026-02-13T07:31:37.535329"
    },
    "139230": {
      "price": 15440.0,
      "source": "naver",
      "timestamp": "2026-02-13T07:31:41.945597"
    },
    "364970": {
      "price": 9030.0,
      "source": "naver",
      "timestamp": "2026-02-13T07:31:19.119635"
    },
    "102120": {
      "price": 12000.0,
      "source": "naver",
      "timestamp": "2026-02-13T07:31:40.858880"
    },
    "102110": {
      "price": 81835.0,
      "source": "naver",
      "timestamp": "2026-02-13T07:31:32.925884"
    },
    "357780": {
      "price": 398000.0,
      "source": "naver",
      "timestamp": "2026-02-13T07:31:39.735397"
    },
    "316140": {
      "price": 38950.0,
      "source": "naver",
      "timestamp": "2026-02-13T07:31:20.231697"
    },
    "196170": {
      "price": 382000.0,
      "source": "naver",
      "timestamp": "2026-02-13T07:31:28.482864"
    },
    "133690": {
      "price": 157705.0,
      "source": "naver",
      "timestamp": "2026-02-13T07:31:13.871777"
    },
    "010120": {
      "price": 661000.0,
      "source": "naver",
      "timestamp": "2026-02-13T07:31:29.641647"
    },
    "005290": {
      "price": 51500.0,
      "source": "naver",
      "timestamp": "2026-02-13T07:31:15.141189"
    },
    "244580": {
      "price": 12970.0,
      "source": "naver",
      "timestamp": "2026-02-13T07:31:21.474177"
    },
    "055550": {
      "price": 102500.0,
      "source": "naver",
      "timestamp": "2026-02-13T07:31:10.284031"
    },
    "015760": {
      "price": 59800.0,
      "source": "naver",
      "timestamp": "2026-02-13T07:31:07.926605"
    },
    "483340": {
      "price": 16560.0,
      "source": "naver",
      "timestamp": "2026-02-13T07:31:38.618341"
    },
    "017960": {
      "price": 34900.0,
      "source": "naver",
      "timestamp": "2026-02-13T07:31:45.265061"
    },
    "428560": {
      "price": 15225.0,
      "source": "naver",
      "timestamp": "2026-02-13T07:31:43.016245"
    },
    "000660": {
      "price": 880000.0,
      "source": "naver",
      "timestamp": "2026-02-13T07:31:30.748991"
    },
    "005930": {
      "price": 181200.0,
      "source": "naver",
      "timestamp": "2026-02-13T07:31:12.776765"
    },
    "103590": {
      "price": 71500.0,
      "source": "naver",
      "timestamp": "2026-02-13T07:31:22.600112"
    },
    "030200": {
      "price": 64500.0,
      "source": "naver",
      "timestamp": "2026-02-13T07:31:34.030105"
    },
    "489790": {
      "price": 61300.0,
      "source": "naver",
      "timestamp": "2026-02-13T07:31:36.396588"
    },
    "229200": {
      "price": 18955.0,
      "source": "naver",
      "timestamp": "2026-02-13T07:31:35.247187"
    },
    "005380": {
      "price": 499000.0,
      "source": "naver",
      "timestamp": "2026-02-13T07:31:11.606614"
    },
    "396500": {
      "price": 29320.0,
      "source": "naver",
      "timestamp": "2026-02-13T07:31:16.781561"
    },
    "URNM": {
      "price": 69.31,
      "source": "yahoo",
      "timestamp": "2026-02-12T16:00:00"
    },
    "URA": {
      "price": 51.75,
      "source": "yahoo",
      "timestamp": "2026-02-12T16:00:00"
    },
    "AAAU": {
      "price": 48.48,
      "source": "yahoo",
      "timestamp": "2026-02-12T16:00:00"
    },
    "SLVR": {
      "price": 62.88,
      "source": "yahoo",
      "timestamp": "2026-02-12T16:00:00"
    },
    "042700": {
      "price": 202500.0,
      "source": "naver",
      "timestamp": "2026-02-13T07:31:24.923245"
    },
    "079550": {
      "price": 460000.0,
      "source": "naver",
      "timestamp": "2026-02-13T07:31:27.434407"
    },
    "440110": {
      "price": 52200.0,
      "source": "naver",
      "timestamp": "2026-02-13T07:31:09.036551"
    }
  }
}