{
  "updated_at": "2026-04-13T01:14:19.958530",
  "prices": {
    "428560": 15990.0,
    "005380": 482500.0,
    "005930": 202000.0,
    "000660": 1032000.0,
    "030200": 62400.0,
    "055550": 98600.0,
    "316140": 34250.0,
    "360750": 25045.0,
    "133690": 164500.0,
    "379810": 24645.0,
    "041510": 85800.0,
    "102110": 87915.0,
    "091160": 102990.0,
    "010120": 180800.0,
    "005290": 52000.0,
    "357780": 423000.0,
    "489790": 74400.0,
    "102120": 11340.0,
    "196170": 350500.0,
    "017960": 49000.0,
    "064350": 207000.0,
    "103590": 83300.0,
    "483340": 19005.0,
    "396500": 33995.0,
    "244580": 11870.0,
    "139230": 15835.0,
    "377300": 52100.0,
    "364970": 7965.0,
    "015760": 42000.0,
    "229200": 18510.0,
    "URNM": 64.44,
    "URA": 50.96,
    "AAAU": 46.95,
    "SLVR": 60.24,
    "042700": 278500.0,
    "079550": 937000.0,
    "440110": 58300.0,
    "329180": 473500.0,
    "006800": 66100.0,
    "034020": 98200.0,
    "ORCL": 138.09,
    "161890": 79650.0,
    "VRT": 295.11,
    "ALM": 17.88
  },
  "price_details": {
    "041510": {
      "price": 85800.0,
      "source": "naver",
      "timestamp": "2026-04-13T01:13:26.702438"
    },
    "064350": {
      "price": 207000.0,
      "source": "naver",
      "timestamp": "2026-04-13T01:14:16.579755"
    },
    "091160": {
      "price": 102990.0,
      "source": "naver",
      "timestamp": "2026-04-13T01:13:25.149755"
    },
    "360750": {
      "price": 25045.0,
      "source": "naver",
      "timestamp": "2026-04-13T01:13:31.679526"
    },
    "379810": {
      "price": 24645.0,
      "source": "naver",
      "timestamp": "2026-04-13T01:13:57.599329"
    },
    "377300": {
      "price": 52100.0,
      "source": "naver",
      "timestamp": "2026-04-13T01:13:29.845154"
    },
    "139230": {
      "price": 15835.0,
      "source": "naver",
      "timestamp": "2026-04-13T01:13:42.175830"
    },
    "364970": {
      "price": 7965.0,
      "source": "naver",
      "timestamp": "2026-04-13T01:13:47.051993"
    },
    "102120": {
      "price": 11340.0,
      "source": "naver",
      "timestamp": "2026-04-13T01:13:28.237498"
    },
    "102110": {
      "price": 87915.0,
      "source": "naver",
      "timestamp": "2026-04-13T01:13:56.044742"
    },
    "357780": {
      "price": 423000.0,
      "source": "naver",
      "timestamp": "2026-04-13T01:14:00.619629"
    },
    "316140": {
      "price": 34250.0,
      "source": "naver",
      "timestamp": "2026-04-13T01:13:34.856787"
    },
    "196170": {
      "price": 350500.0,
      "source": "naver",
      "timestamp": "2026-04-13T01:13:50.163083"
    },
    "133690": {
      "price": 164500.0,
      "source": "naver",
      "timestamp": "2026-04-13T01:14:08.115449"
    },
    "010120": {
      "price": 180800.0,
      "source": "naver",
      "timestamp": "2026-04-13T01:13:33.279200"
    },
    "005290": {
      "price": 52000.0,
      "source": "naver",
      "timestamp": "2026-04-13T01:14:01.994329"
    },
    "244580": {
      "price": 11870.0,
      "source": "naver",
      "timestamp": "2026-04-13T01:14:06.696551"
    },
    "055550": {
      "price": 98600.0,
      "source": "naver",
      "timestamp": "2026-04-13T01:13:54.435724"
    },
    "015760": {
      "price": 42000.0,
      "source": "naver",
      "timestamp": "2026-04-13T01:13:45.312287"
    },
    "483340": {
      "price": 19005.0,
      "source": "naver",
      "timestamp": "2026-04-13T01:14:13.870294"
    },
    "017960": {
      "price": 49000.0,
      "source": "naver",
      "timestamp": "2026-04-13T01:13:51.694237"
    },
    "428560": {
      "price": 15990.0,
      "source": "naver",
      "timestamp": "2026-04-13T01:13:21.830788"
    },
    "000660": {
      "price": 1032000.0,
      "source": "naver",
      "timestamp": "2026-04-13T01:13:48.539674"
    },
    "005930": {
      "price": 202000.0,
      "source": "naver",
      "timestamp": "2026-04-13T01:13:40.834447"
    },
    "103590": {
      "price": 83300.0,
      "source": "naver",
      "timestamp": "2026-04-13T01:13:23.546508"
    },
    "030200": {
      "price": 62400.0,
      "source": "naver",
      "timestamp": "2026-04-13T01:13:43.549755"
    },
    "489790": {
      "price": 74400.0,
      "source": "naver",
      "timestamp": "2026-04-13T01:13:37.660365"
    },
    "229200": {
      "price": 18510.0,
      "source": "naver",
      "timestamp": "2026-04-13T01:14:09.446998"
    },
    "005380": {
      "price": 482500.0,
      "source": "naver",
      "timestamp": "2026-04-13T01:14:05.316130"
    },
    "396500": {
      "price": 33995.0,
      "source": "naver",
      "timestamp": "2026-04-13T01:14:15.225453"
    },
    "URNM": {
      "price": 64.44,
      "source": "yahoo",
      "timestamp": "2026-04-12T16:00:00"
    },
    "URA": {
      "price": 50.96,
      "source": "yahoo",
      "timestamp": "2026-04-12T16:00:00"
    },
    "AAAU": {
      "price": 46.95,
      "source": "yahoo",
      "timestamp": "2026-04-12T16:00:00"
    },
    "SLVR": {
      "price": 60.24,
      "source": "yahoo",
      "timestamp": "2026-04-12T16:00:00"
    },
    "042700": {
      "price": 278500.0,
      "source": "naver",
      "timestamp": "2026-04-13T01:14:10.958007"
    },
    "079550": {
      "price": 937000.0,
      "source": "naver",
      "timestamp": "2026-04-13T01:13:36.243374"
    },
    "440110": {
      "price": 58300.0,
      "source": "naver",
      "timestamp": "2026-04-13T01:14:12.504263"
    },
    "329180": {
      "price": 473500.0,
      "source": "naver",
      "timestamp": "2026-04-13T01:13:39.312057"
    },
    "006800": {
      "price": 66100.0,
      "source": "naver",
      "timestamp": "2026-04-13T01:13:53.066145"
    },
    "034020": {
      "price": 98200.0,
      "source": "naver",
      "timestamp": "2026-04-13T01:14:03.452433"
    },
    "ORCL": {
      "price": 138.09,
      "source": "yahoo",
      "timestamp": "2026-04-12T16:00:00"
    },
    "161890": {
      "price": 79650.0,
      "source": "naver",
      "timestamp": "2026-04-13T01:13:59.227763"
    },
    "VRT": {
      "price": 295.11,
      "source": "yahoo",
      "timestamp": "2026-04-12T16:00:00"
    },
    "ALM": {
      "price": 17.88,
      "source": "yahoo",
      "timestamp": "2026-04-12T16:00:00"
    }
  }
}